---
list_title: Java Part 2
layout: post
---

## 数据类型，变量，常量

### Java的数据类型划分

- 基本的数据类型(primitive types):
    - 数值
        - 整数: byte(1), short(2), int(4) ,long(8)
            - 二进制数以`0b`或`0B`开头,`0b00010010`(Java 7以上)
            - Java语言中整形默认为 `int`
            - 声明`long`型：`long a = 3L`后面加`l`或`L`
            - Java中没有“无符号数”, C中的`unsigned int`在Java中用`long`表示
        - 浮点型: float(4), double(8)
            - 科学技术法:
                - `3.14e2`,`3.14E2`
            - Java中浮点型默认为`double`，如果想使用`float`需要:`float a = 3.45f`末尾加`f`
    - 字符型:
        - <mark>Java中的字符用Unicode编码，每个字符两个字节</mark>
            - 可用16进制表示
            - `char c1 = '\uff09 '`
    - 布尔型: boolean
        - 只能用`true`或`false`

- 引用数据类型(reference types):
    - 类: class
    - 接口: interface
    - 数组
- 差别:
	- 基本类型: 变量在栈
		- `double d = 3`
	- 引用类型: 变量引用到堆
		- `Person p = new Person()`
- 赋值:
	- `double d2 = d; `复制的是值
	- `Person p2 = p;` 复制的是引用

## 运算符与表达式

### 运算符

- 位运算
	- `~`按位取反
	- `&`按位与
	- `|`按位或
	- `^`按位异或

- 移位运算
	- 左移`a<<b`将二进制形式的`a`逐位左移`b`位，空出的补0
	- 带符号右移：`a>>b`将二进制形式的`a`逐位右移`b`位，高位补符号位
	- 无符号右移：`a>>>b`将二进制形式的`a`逐位右移`b`位，高位补符号位
	- 适用于数据类型：byte, short, char, int, long
	- 对于低于int型的数据，系统将先自动换为int型，再移位
	- 对于int型整数移位 `a>>b`, 系统先将b对32取模，得到的结果才是真正的移位数
	- 对于long型整数移位 `a>>b`, 系统先将b对64取模，得到的结果才是真正的移位数

###表达式

- a++的副作用:

```java
public class Test{
    public static void main(String[] args){
        int a = 2;
        int b = a++ + ++a;
        System.out.println(b); 
   }
}
```

上面代码执行结果为6，为什么呢? 使用javap -c 反汇编查看:

```java
Compiled from "Test.java"
public class Test {
  public Test();
    Code:
       0: aload_0
       1: invokespecial #1                  // Method java/lang/Object."<init>":()V
       4: return

  public static void main(java.lang.String[]);
    Code:
       0: iconst_2
       1: istore_1
       2: iload_1
       3: iinc          1, 1
       6: iinc          1, 1
       9: iload_1
      10: iadd
      11: istore_2
      12: getstatic     #2                  // Field java/lang/System.out:Ljava/io/PrintStream;
      15: iload_2
      16: invokevirtual #3                  // Method java/io/PrintStream.println:(I)V
      19: return
}
```

上面是虚拟机的指令:

```
`iconst_2`:定义常量
`istore_1`:将常量存入寄存器1
`iload_1`:从寄存器中读取a = 2
`iinc`: 值+1 => a++ => a = 3
`iinc`: 值+1 => ++a => a = 4
`iload_1`:从寄存器中读取a = 2
`iadd`: 2+4 = 6
`istore_2`: 将6保存到寄存器2，也就赋值给b
```

## Control Flow

### 程序中3种基本流程

- 顺序，分支(if)，循环
- 证明所有程序都可由这三种过程组合来完成
- <mark>C语言中的问题</mark>
    - 没有expression的概念，全是statement，例如没有`x+y;`这种没意义的语句，也没有逗号表达式的概念

- 使用Switch
	- 变量后面可以是整数，字符，字符串
	- `case`后面是常量
	- 注意`break`

- 带标签的continue和break
    - 计算100以内的素数:

    ```java
    public class chap3{
        public static void main(String[] args){
            //计算1~100以内的素数
            out:
            for(int i=1; i<=100; i++){
                for(int j=2; j<i; j++){
                    if(i%j == 0)
                        continue out;
                }
                System.out.println(i);
            }
        }
    }
    ```

## 数组

### 一维数组:

- 一维数组的声明：
	- `int[] a;`
	- `double[] b;`
	- `Mydata[] c;` 

-  注意，方括号可以写到变量名前面，也可以写到后面
- 数组定义和分配空间分别执行:

```java
int []a = new int[3]
a[0] = 1;
a[1] = 2;
a[3] = 3;
```

- Java语言中声明数组时不能指定长度：

```c
int a[5]; //error
```

- 数组时引用类型，必须在heap上分配空间:
	- `int []a = new int[5];`
	- 这里a只是一个引用
- 初始化:
	- 静态初始化:定义数组时就分配空间并初始化

	```java	
	int[] a = {3,9,8};
	int[] b = new int[]{3,9,8};
	Mydata[] dates = { new Mydata(22,8), new Mydata(99,8)};
	```
	
	- 注意最后可以多一个逗号:如`{3,9,8,}`
	- 数组一经分配空间，其中的元素会被赋值为默认值0或`null`,如:

	```java
	int []a = new int[5]
	//a中的元素为0
	```
	
- 数组元素的引用:
	- index为下标:`a[3],b[i]...`

- 快速枚举:

```java
int[] ages = new int[10];
for(int age : ages){
	print(age);
}

```

### 多维数组

- 二维数组是数组的数组

```java
int [][]a = { {1,2}, {3,4}, {5,6} };
int [][]t = new int [3][]
t[0] = new int[2];
t[1] = new int[3];
t[2] = new int[4]; 
```


